[{"name":"Java","path":"api/tags/Java.json","slug":"Java","count":3},{"name":"Linux","path":"api/tags/Linux.json","slug":"Linux","count":2},{"name":"GraphQL","path":"api/tags/GraphQL.json","slug":"GraphQL","count":1},{"name":"Kafka","path":"api/tags/Kafka.json","slug":"Kafka","count":1},{"name":"Pulsar","path":"api/tags/Pulsar.json","slug":"Pulsar","count":2},{"name":"Network","path":"api/tags/Network.json","slug":"Network","count":1},{"name":"Redis","path":"api/tags/Redis.json","slug":"Redis","count":1},{"name":"Mysql","path":"api/tags/Mysql.json","slug":"Mysql","count":2},{"name":"RegExp","path":"api/tags/RegExp.json","slug":"RegExp","count":1},{"name":"vps","path":"api/tags/vps.json","slug":"vps","count":2},{"name":"MacOS","path":"api/tags/MacOS.json","slug":"MacOS","count":1},{"name":"Zookeeper","path":"api/tags/Zookeeper.json","slug":"Zookeeper","count":1},{"name":"i18n","path":"api/tags/i18n.json","slug":"i18n","count":1},{"name":"idea","path":"api/tags/idea.json","slug":"idea","count":2},{"name":"tools","path":"api/tags/tools.json","slug":"tools","count":2}]